{
    "version": "1.5.49",
    "description": "Crystal programming language preview @ 24360482d",
    "homepage": "https://crystal-lang.org/",
    "license": {
        "identifier": "Apache-2.0",
        "url": "https://github.com/crystal-lang/crystal/blob/master/LICENSE"
    },
    "url": [
        "https://nightly.link/crystal-lang/crystal/actions/artifacts/370289117.zip"
    ],
    "hash": [
        "85B846D57C27A70551ABCA54A2559C09B6AF23FF70C3E5350B91E2D112C1ABA4"
    ],
    "depends": [
        "vswhere"
    ],
    "bin": [
        "crystal.exe",
        "shards.exe"
    ],
    "post_install": [
        "If (Test-Path $env:LOCALAPPDATA\\crystal\\cache) { rm -r -fo $env:LOCALAPPDATA\\crystal\\cache}"
    ]
}
