{
    "version": "17.0",
    "description": "Visual Studio 2022 C++ Build Tools",
    "url": "https://aka.ms/vs/17/release/vs_BuildTools.exe",
    "hash": "3574B2FAE00D468A552FB35ECD5C40DA4EF2CB9FAE9E919A3C6405465BE4DA29",
    "installer": {
        "args": "--passive --norestart --wait --add Microsoft.VisualStudio.Workload.VCTools --add Microsoft.VisualStudio.Component.VC.ATL --includeRecommended",
        "keep": true
    },
    "uninstaller": {
        "file": "vs_BuildTools.exe",
        "args": "--passive --norestart --wait --remove Microsoft.VisualStudio.Workload.VCTools --remove Microsoft.VisualStudio.Component.VC.ATL --includeRecommended"
    }
}
